AdvertsAPI/__init__.py
AdvertsAPI/_version.py
AdvertsAPI/ad_info.py
AdvertsAPI/category.py
AdvertsAPI/product_info.py
AdvertsAPI/utils.py
AdvertsAPI-0.0.1.dist-info/LICENSE
AdvertsAPI-0.0.1.dist-info/METADATA
AdvertsAPI-0.0.1.dist-info/WHEEL
AdvertsAPI-0.0.1.dist-info/top_level.txt
AdvertsAPI-0.0.1.dist-info/RECORD
