Metadata-Version: 2.1
Name: AdvertsAPI
Version: 0.0.1
Summary: An unofficial API for the community based Irish marketplace, adverts.ie
Home-page: https://github.com/ahmedhamedaly/Adverts-API
Author: Ahmed Hamed Aly
Author-email: hamedala@tcd.ie
License: UNKNOWN
Platform: UNKNOWN
Classifier: Programming Language :: Python :: 3
Classifier: License :: OSI Approved :: MIT License
Classifier: Operating System :: OS Independent
Requires-Python: >=3.6
